breathXplorer/__init__.py
breathXplorer/cluster.py
breathXplorer/container.py
breathXplorer/extract.py
breathXplorer/file_io.py
breathXplorer/find_peak.py
breathXplorer/utils.py
breathXplorer-0.2.7.dist-info/LICENSE
breathXplorer-0.2.7.dist-info/METADATA
breathXplorer-0.2.7.dist-info/WHEEL
breathXplorer-0.2.7.dist-info/top_level.txt
breathXplorer-0.2.7.dist-info/RECORD
