Metadata-Version: 2.1
Name: breathXplorer
Version: 0.2.7
Summary: A toolkit for breath metabolomics analysis
Home-page: https://github.com/wykswr/breathXplorer
Author: wykswr
Author-email: bifocal.above.0y@icloud.com
License: MIT
Classifier: Development Status :: 3 - Alpha
Classifier: Intended Audience :: Developers
Classifier: License :: OSI Approved :: MIT License
Classifier: Programming Language :: Python :: 3
Classifier: Programming Language :: Python :: 3.8
Classifier: Programming Language :: Python :: 3.9
Classifier: Programming Language :: Python :: 3.10
Classifier: Programming Language :: Python :: 3.11
Classifier: Programming Language :: Python :: 3.12
License-File: LICENSE
Requires-Dist: lxml
Requires-Dist: numba
Requires-Dist: numpy
Requires-Dist: pandas
Requires-Dist: pyteomics
Requires-Dist: scikit-learn
Requires-Dist: scipy
